ChangeLog
LICENSE
MANIFEST.in
README.md
requirements.txt
setup.py
codimension/__init__.py
codimension/cdmverspec.py
codimension/codimension.py
codimension.egg-info/PKG-INFO
codimension.egg-info/SOURCES.txt
codimension.egg-info/dependency_links.txt
codimension.egg-info/entry_points.txt
codimension.egg-info/requires.txt
codimension.egg-info/top_level.txt
codimension/analysis/__init__.py
codimension/analysis/disasm.py
codimension/analysis/ierrors.py
codimension/analysis/notused.py
codimension/autocomplete/__init__.py
codimension/autocomplete/bufferutils.py
codimension/autocomplete/completelists.py
codimension/debugger/__init__.py
codimension/debugger/bpointviewer.py
codimension/debugger/bputils.py
codimension/debugger/bpwp.py
codimension/debugger/breakpoint.py
codimension/debugger/breakpointmodel.py
codimension/debugger/calltraceviewer.py
codimension/debugger/clientexcptviewer.py
codimension/debugger/context.py
codimension/debugger/editbreakpoint.py
codimension/debugger/excpt.py
codimension/debugger/ignoredexcptviewer.py
codimension/debugger/modifiedunsaved.py
codimension/debugger/server.py
codimension/debugger/stackviewer.py
codimension/debugger/threadsviewer.py
codimension/debugger/varfilters.py
codimension/debugger/variableitems.py
codimension/debugger/variablesbrowser.py
codimension/debugger/variablesviewer.py
codimension/debugger/viewvariable.py
codimension/debugger/watchpoint.py
codimension/debugger/watchpointmodel.py
codimension/debugger/wpointviewer.py
codimension/debugger/client/__init__.py
codimension/debugger/client/asyncfile_cdm_dbg.py
codimension/debugger/client/base_cdm_dbg.py
codimension/debugger/client/bp_wp_cdm_dbg.py
codimension/debugger/client/cdm_dbg_utils.py
codimension/debugger/client/client_cdm_dbg.py
codimension/debugger/client/client_cdm_profile.py
codimension/debugger/client/client_cdm_run.py
codimension/debugger/client/clientbase_cdm_dbg.py
codimension/debugger/client/getpass.py
codimension/debugger/client/outredir_cdm_dbg.py
codimension/debugger/client/protocol_cdm_dbg.py
codimension/debugger/client/threadextension_cdm_dbg.py
codimension/debugger/client/variables_cdm_dbg.py
codimension/diagram/__init__.py
codimension/diagram/importsdgm.py
