Metadata-Version: 1.2
Name: codimension
Version: 4.9.0
Summary: Experimental Python 3 IDE which aims at both textual and graphical representation of a code. The graphics is automatically re-generated while the code is typed
Home-page: https://github.com/SergeySatskiy/codimension
Author: Sergey Satskiy
Author-email: sergey.satskiy@gmail.com
License: GPLv3
Platform: any
Classifier: Development Status :: 5 - Production/Stable
Classifier: Intended Audience :: Developers
Classifier: License :: OSI Approved :: GNU General Public License (GPL)
Classifier: Operating System :: POSIX :: Linux
Classifier: Programming Language :: Python :: 3
Requires-Python: >=3.5, <3.9
